mulog/__init__.py
mulog/condloading.py
mulog/diagloading.py
mulog/gaussian_denoisers.py
mulog/midal_algorithm.py
mulog/mulog_algorithm.py
mulog/mulog_examples.py
mulog/mulog_synthetic_example.py
mulog/pnp_admm.py
mulog/prox.py
mulog/sar_image_generation.py
mulog/sar_image_rendering.py
mulog/stabmatrices.py
mulog/tools.py
mulog/artifacts/README
mulog/artifacts/__init__.py
mulog/artifacts/labrador_sentinel1.pickle.gz
mulog/artifacts/sanfrancisco_airsar.pickle.gz
mulog/artifacts/shanghai_sentinel1.pickle.gz
mulog/artifacts/tsukaba_pisar.pickle.gz
mulog/hermitian_matrix_field/__init__.py
mulog/hermitian_matrix_field/channel_decomposition.py
mulog/hermitian_matrix_field/linear_algebra.py
mulog/hermitian_matrix_field/log_channel_decomposition.py
mulog/hermitian_matrix_field/matrix_exponentials.py
mulog-0.0.4.dist-info/METADATA
mulog-0.0.4.dist-info/WHEEL
mulog-0.0.4.dist-info/top_level.txt
mulog-0.0.4.dist-info/RECORD
