Metadata-Version: 2.1
Name: mulog
Version: 0.0.4
Summary: Multi-Channel Logarithm with Gaussian Denoiser - A (Pol/In)SAR image speckle reduction algorithm.
Home-page: https://www.charles-deledalle.fr/pages/mulog
Author: Charles Deledalle, Sébastien Mounier, Cristiano Ulondu Mendes
Author-email: charles.deledalle@gmail.com
License: cecill
Project-URL: Source, https://bitbucket.org/charles_deledalle/mulog2022-python/
Keywords: SAR,PolSAR,InSAR,speckle,filtering,images,wishart,admm,pnp
Requires-Python: >=3.10
Requires-Dist: bm3d >=4.0.1
Requires-Dist: nptyping >=2.4.0
Requires-Dist: attrs >=23.1.0
Requires-Dist: matplotlib >=3.7.2
Requires-Dist: typing-extensions >=4.7.1
Requires-Dist: strenum >=0.4.15
Requires-Dist: scikit-image >=0.21.0
